nrdtech_utils/__init__.py
nrdtech_utils/deprecated.py
nrdtech_utils/list_helper.py
nrdtech_utils/primitive_utils.py
nrdtech_utils-0.0.3.dist-info/LICENSE
nrdtech_utils-0.0.3.dist-info/WHEEL
nrdtech_utils-0.0.3.dist-info/METADATA
nrdtech_utils-0.0.3.dist-info/RECORD
